onnx_quantize/__init__.py
onnx_quantize/opset.py
onnx_quantize/quantize.py
onnx_quantize/core/__init__.py
onnx_quantize/core/_calibrate.py
onnx_quantize/core/_dtypes.py
onnx_quantize/core/_gptq.py
onnx_quantize/core/_pack.py
onnx_quantize/core/_qconfig.py
onnx_quantize/core/_rtn.py
onnx_quantize/pre_rules/__init__.py
onnx_quantize/pre_rules/standarize_gemm.py
onnx_quantize/qfunctions/__init__.py
onnx_quantize/qfunctions/qgemm.py
onnx_quantize/qfunctions/qmatmul.py
onnx_quantize/qfunctions/register.py
onnx_quantize/qrules/__init__.py
onnx_quantize/qrules/base.py
onnx_quantize/qrules/gemm_to_qgemm.py
onnx_quantize/qrules/matmul_to_qmatmul.py
onnx_quantize-0.2.0.dist-info/licenses/LICENSE
onnx_quantize-0.2.0.dist-info/METADATA
onnx_quantize-0.2.0.dist-info/WHEEL
onnx_quantize-0.2.0.dist-info/top_level.txt
onnx_quantize-0.2.0.dist-info/RECORD
