Metadata-Version: 2.4
Name: onnx_quantize
Version: 0.2.0
Summary: ONNX Quantization Framework
Author-email: Ayoub Bih <ayoubbih119@gmail.com>
Requires-Python: >=3.10
License-File: LICENSE
Requires-Dist: onnxscript
Requires-Dist: onnxruntime
Requires-Dist: pydantic>=2.0
Provides-Extra: test
Requires-Dist: pytest; extra == "test"
Provides-Extra: integration
Requires-Dist: pytest; extra == "integration"
Requires-Dist: optimum-onnx; extra == "integration"
Requires-Dist: datasets; extra == "integration"
Dynamic: license-file
